eses/__init__.py
eses/version.py
eses-1.0.8.dist-info/licenses/LICENSE
eses-1.0.8.dist-info/METADATA
eses-1.0.8.dist-info/WHEEL
eses-1.0.8.dist-info/top_level.txt
eses-1.0.8.dist-info/RECORD
